{
    "out-cornell-aniso-q.pbrt-iBDPT-sHALTON-n008.exr": 0.20104330347527283,
    "out-cornell-aniso-q.pbrt-iBDPT-sHALTON-n032.exr": 0.200294455145269,
    "out-cornell-aniso-q.pbrt-iBDPT-sHALTON-n128.exr": 0.1980617288487128,
    "out-cornell-aniso-q.pbrt-iBDPT-sPOISSON-n008.exr": 0.20016206605901007,
    "out-cornell-aniso-q.pbrt-iBDPT-sPOISSON-n032.exr": 0.1997034006504244,
    "out-cornell-aniso-q.pbrt-iBDPT-sPOISSON-n128.exr": 0.20567521294769,
    "out-cornell-aniso-q.pbrt-iBDPT-sRANDOM-n008.exr": 0.2029874099492719,
    "out-cornell-aniso-q.pbrt-iBDPT-sRANDOM-n032.exr": 0.19863051385651107,
    "out-cornell-aniso-q.pbrt-iBDPT-sRANDOM-n128.exr": 0.19823374613184658,
    "out-cornell-aniso-q.pbrt-iBDPT-sSOBOL-n008.exr": 0.20046145606607352,
    "out-cornell-aniso-q.pbrt-iBDPT-sSOBOL-n032.exr": 0.1981890057660637,
    "out-cornell-aniso-q.pbrt-iBDPT-sSOBOL-n128.exr": 0.19780309157007253,
    "out-cornell-aniso-q.pbrt-iPATH-sHALTON-n008.exr": 3.4765461674774083,
    "out-cornell-aniso-q.pbrt-iPATH-sHALTON-n032.exr": 0.3749675235713775,
    "out-cornell-aniso-q.pbrt-iPATH-sHALTON-n128.exr": 0.061762779933227055,
    "out-cornell-aniso-q.pbrt-iPATH-sPOISSON-n008.exr": 0.7571112040092062,
    "out-cornell-aniso-q.pbrt-iPATH-sPOISSON-n032.exr": 0.7487606394273646,
    "out-cornell-aniso-q.pbrt-iPATH-sPOISSON-n128.exr": 0.05183717871609079,
    "out-cornell-aniso-q.pbrt-iPATH-sRANDOM-n008.exr": 0.15454677125994748,
    "out-cornell-aniso-q.pbrt-iPATH-sRANDOM-n032.exr": 0.32751721403189893,
    "out-cornell-aniso-q.pbrt-iPATH-sRANDOM-n128.exr": 0.11217007321081593,
    "out-cornell-aniso-q.pbrt-iPATH-sSOBOL-n008.exr": 0.2077088536715807,
    "out-cornell-aniso-q.pbrt-iPATH-sSOBOL-n032.exr": 0.21948136030172744,
    "out-cornell-aniso-q.pbrt-iPATH-sSOBOL-n128.exr": 0.08305867347753638,
    "out-cornell-aniso-q.pbrt-iWHITTED-sHALTON-n008.exr": 0.10241422844444702,
    "out-cornell-aniso-q.pbrt-iWHITTED-sHALTON-n032.exr": 0.0824545732326644,
    "out-cornell-aniso-q.pbrt-iWHITTED-sHALTON-n128.exr": 0.08113597028306437,
    "out-cornell-aniso-q.pbrt-iWHITTED-sPOISSON-n008.exr": 0.0813840945693409,
    "out-cornell-aniso-q.pbrt-iWHITTED-sPOISSON-n032.exr": 0.13755971031843203,
    "out-cornell-aniso-q.pbrt-iWHITTED-sPOISSON-n128.exr": 0.08176692485808904,
    "out-cornell-aniso-q.pbrt-iWHITTED-sRANDOM-n008.exr": 0.0813325686852763,
    "out-cornell-aniso-q.pbrt-iWHITTED-sRANDOM-n032.exr": 0.08101999360848534,
    "out-cornell-aniso-q.pbrt-iWHITTED-sRANDOM-n128.exr": 0.12909140261332377,
    "out-cornell-aniso-q.pbrt-iWHITTED-sSOBOL-n008.exr": 0.08115567558532809,
    "out-cornell-aniso-q.pbrt-iWHITTED-sSOBOL-n032.exr": 0.08109122087825853,
    "out-cornell-aniso-q.pbrt-iWHITTED-sSOBOL-n128.exr": 0.08378989371473981,
    "out-dof-dragons-aniso-q.pbrt-iBDPT-sHALTON-n008.exr": 0.008892013567365437,
    "out-dof-dragons-aniso-q.pbrt-iBDPT-sHALTON-n032.exr": 0.022291401008945957,
    "out-dof-dragons-aniso-q.pbrt-iBDPT-sHALTON-n128.exr": 0.12311794412003592,
    "out-dof-dragons-aniso-q.pbrt-iBDPT-sPOISSON-n008.exr": 0.010498958063758924,
    "out-dof-dragons-aniso-q.pbrt-iBDPT-sPOISSON-n032.exr": 0.020293412574367172,
    "out-dof-dragons-aniso-q.pbrt-iBDPT-sPOISSON-n128.exr": 0.0302661004788069,
    "out-dof-dragons-aniso-q.pbrt-iBDPT-sRANDOM-n008.exr": 0.016307235615589666,
    "out-dof-dragons-aniso-q.pbrt-iBDPT-sRANDOM-n032.exr": 5.888664834214445,
    "out-dof-dragons-aniso-q.pbrt-iBDPT-sRANDOM-n128.exr": 0.00448560316018441,
    "out-dof-dragons-aniso-q.pbrt-iBDPT-sSOBOL-n008.exr": 0.008051217567816368,
    "out-dof-dragons-aniso-q.pbrt-iBDPT-sSOBOL-n032.exr": 0.0026354817702476663,
    "out-dof-dragons-aniso-q.pbrt-iBDPT-sSOBOL-n128.exr": 0.004623203763671411,
    "out-dof-dragons-aniso-q.pbrt-iPATH-sHALTON-n008.exr": 0.0062468467116882495,
    "out-dof-dragons-aniso-q.pbrt-iPATH-sHALTON-n032.exr": 0.018709183143112287,
    "out-dof-dragons-aniso-q.pbrt-iPATH-sHALTON-n128.exr": 0.0015763914220215873,
    "out-dof-dragons-aniso-q.pbrt-iPATH-sPOISSON-n008.exr": 0.03159331330161805,
    "out-dof-dragons-aniso-q.pbrt-iPATH-sPOISSON-n032.exr": 0.0022514146525998797,
    "out-dof-dragons-aniso-q.pbrt-iPATH-sPOISSON-n128.exr": 0.012984993412054627,
    "out-dof-dragons-aniso-q.pbrt-iPATH-sRANDOM-n008.exr": 0.011570570756383472,
    "out-dof-dragons-aniso-q.pbrt-iPATH-sRANDOM-n032.exr": 0.002656106913045257,
    "out-dof-dragons-aniso-q.pbrt-iPATH-sRANDOM-n128.exr": 0.0012866636863727242,
    "out-dof-dragons-aniso-q.pbrt-iPATH-sSOBOL-n008.exr": 0.0048636893811863985,
    "out-dof-dragons-aniso-q.pbrt-iPATH-sSOBOL-n032.exr": 0.004461532060568649,
    "out-dof-dragons-aniso-q.pbrt-iPATH-sSOBOL-n128.exr": 0.0007858092480310819,
    "out-dof-dragons-aniso-q.pbrt-iWHITTED-sHALTON-n008.exr": 1.6404390055307736,
    "out-dof-dragons-aniso-q.pbrt-iWHITTED-sHALTON-n032.exr": 0.4798411844028334,
    "out-dof-dragons-aniso-q.pbrt-iWHITTED-sHALTON-n128.exr": 0.3749778857249894,
    "out-dof-dragons-aniso-q.pbrt-iWHITTED-sPOISSON-n008.exr": 0.8038745540161106,
    "out-dof-dragons-aniso-q.pbrt-iWHITTED-sPOISSON-n032.exr": 0.5024783679299284,
    "out-dof-dragons-aniso-q.pbrt-iWHITTED-sPOISSON-n128.exr": 0.08803819964012478,
    "out-dof-dragons-aniso-q.pbrt-iWHITTED-sRANDOM-n008.exr": 0.9068814105127918,
    "out-dof-dragons-aniso-q.pbrt-iWHITTED-sRANDOM-n032.exr": 0.6117958920618201,
    "out-dof-dragons-aniso-q.pbrt-iWHITTED-sRANDOM-n128.exr": 1.4411901347660514,
    "out-dof-dragons-aniso-q.pbrt-iWHITTED-sSOBOL-n008.exr": 0.7955408328246065,
    "out-dof-dragons-aniso-q.pbrt-iWHITTED-sSOBOL-n032.exr": 0.4442761908024288,
    "out-dof-dragons-aniso-q.pbrt-iWHITTED-sSOBOL-n128.exr": 0.44135700977099573,
    "out-killeroo-aniso-q.pbrt-iBDPT-sHALTON-n008.exr": 0.07082033634745441,
    "out-killeroo-aniso-q.pbrt-iBDPT-sHALTON-n032.exr": 0.021814067656414804,
    "out-killeroo-aniso-q.pbrt-iBDPT-sHALTON-n128.exr": 0.012014973047132178,
    "out-killeroo-aniso-q.pbrt-iBDPT-sPOISSON-n008.exr": 0.08273588955019268,
    "out-killeroo-aniso-q.pbrt-iBDPT-sPOISSON-n032.exr": 0.018643741345544668,
    "out-killeroo-aniso-q.pbrt-iBDPT-sPOISSON-n128.exr": 0.056235157978672054,
    "out-killeroo-aniso-q.pbrt-iBDPT-sRANDOM-n008.exr": 0.07213613643647801,
    "out-killeroo-aniso-q.pbrt-iBDPT-sRANDOM-n032.exr": 0.027218639429516852,
    "out-killeroo-aniso-q.pbrt-iBDPT-sRANDOM-n128.exr": 0.012838414749326446,
    "out-killeroo-aniso-q.pbrt-iBDPT-sSOBOL-n008.exr": 0.07662801717370807,
    "out-killeroo-aniso-q.pbrt-iBDPT-sSOBOL-n032.exr": 0.023540775641913463,
    "out-killeroo-aniso-q.pbrt-iBDPT-sSOBOL-n128.exr": 0.012161910221698824,
    "out-killeroo-aniso-q.pbrt-iPATH-sHALTON-n008.exr": 0.05097384267417412,
    "out-killeroo-aniso-q.pbrt-iPATH-sHALTON-n032.exr": 2.946356096643171,
    "out-killeroo-aniso-q.pbrt-iPATH-sHALTON-n128.exr": 0.1927336707769938,
    "out-killeroo-aniso-q.pbrt-iPATH-sPOISSON-n008.exr": 0.0791034672055393,
    "out-killeroo-aniso-q.pbrt-iPATH-sPOISSON-n032.exr": 0.019260181542346776,
    "out-killeroo-aniso-q.pbrt-iPATH-sPOISSON-n128.exr": 0.045931758895994684,
    "out-killeroo-aniso-q.pbrt-iPATH-sRANDOM-n008.exr": 0.05793808656342624,
    "out-killeroo-aniso-q.pbrt-iPATH-sRANDOM-n032.exr": 0.019449581223707546,
    "out-killeroo-aniso-q.pbrt-iPATH-sRANDOM-n128.exr": 0.013042264324655033,
    "out-killeroo-aniso-q.pbrt-iPATH-sSOBOL-n008.exr": 0.049265324794780053,
    "out-killeroo-aniso-q.pbrt-iPATH-sSOBOL-n032.exr": 0.011762479302654952,
    "out-killeroo-aniso-q.pbrt-iPATH-sSOBOL-n128.exr": 0.0899765796625788,
    "out-killeroo-aniso-q.pbrt-iWHITTED-sHALTON-n008.exr": 0.027565338858359288,
    "out-killeroo-aniso-q.pbrt-iWHITTED-sHALTON-n032.exr": 0.021960576971977758,
    "out-killeroo-aniso-q.pbrt-iWHITTED-sHALTON-n128.exr": 0.05434496375145699,
    "out-killeroo-aniso-q.pbrt-iWHITTED-sPOISSON-n008.exr": 0.03526092833519384,
    "out-killeroo-aniso-q.pbrt-iWHITTED-sPOISSON-n032.exr": 0.028636249945080527,
    "out-killeroo-aniso-q.pbrt-iWHITTED-sPOISSON-n128.exr": 0.03360503320154696,
    "out-killeroo-aniso-q.pbrt-iWHITTED-sRANDOM-n008.exr": 0.29829455033314445,
    "out-killeroo-aniso-q.pbrt-iWHITTED-sRANDOM-n032.exr": 0.025286696778589513,
    "out-killeroo-aniso-q.pbrt-iWHITTED-sRANDOM-n128.exr": 0.026914686929130592,
    "out-killeroo-aniso-q.pbrt-iWHITTED-sSOBOL-n008.exr": 0.032098578627479044,
    "out-killeroo-aniso-q.pbrt-iWHITTED-sSOBOL-n032.exr": 0.026472903348485354,
    "out-killeroo-aniso-q.pbrt-iWHITTED-sSOBOL-n128.exr": 0.021889317005321693,
    "out-teapot-cornell-aniso-q.pbrt-iBDPT-sHALTON-n008.exr": 0.001754435047879516,
    "out-teapot-cornell-aniso-q.pbrt-iBDPT-sHALTON-n032.exr": 0.0016193852118545772,
    "out-teapot-cornell-aniso-q.pbrt-iBDPT-sHALTON-n128.exr": 0.0015828248181666412,
    "out-teapot-cornell-aniso-q.pbrt-iBDPT-sPOISSON-n008.exr": 0.001728796183909506,
    "out-teapot-cornell-aniso-q.pbrt-iBDPT-sPOISSON-n032.exr": 0.0016827785907761747,
    "out-teapot-cornell-aniso-q.pbrt-iBDPT-sPOISSON-n128.exr": 0.0031496148142442703,
    "out-teapot-cornell-aniso-q.pbrt-iBDPT-sRANDOM-n008.exr": 0.001761323296780057,
    "out-teapot-cornell-aniso-q.pbrt-iBDPT-sRANDOM-n032.exr": 0.0016130253247314398,
    "out-teapot-cornell-aniso-q.pbrt-iBDPT-sRANDOM-n128.exr": 0.0015897462038004047,
    "out-teapot-cornell-aniso-q.pbrt-iBDPT-sSOBOL-n008.exr": 0.0017082160001039212,
    "out-teapot-cornell-aniso-q.pbrt-iBDPT-sSOBOL-n032.exr": 0.001617397676332752,
    "out-teapot-cornell-aniso-q.pbrt-iBDPT-sSOBOL-n128.exr": 0.0015847448294831615,
    "out-teapot-cornell-aniso-q.pbrt-iPATH-sHALTON-n008.exr": 0.0003373404439920813,
    "out-teapot-cornell-aniso-q.pbrt-iPATH-sHALTON-n032.exr": 7.247066148956716e-05,
    "out-teapot-cornell-aniso-q.pbrt-iPATH-sHALTON-n128.exr": 1.4186979763522504e-05,
    "out-teapot-cornell-aniso-q.pbrt-iPATH-sPOISSON-n008.exr": 0.00039808151151554287,
    "out-teapot-cornell-aniso-q.pbrt-iPATH-sPOISSON-n032.exr": 8.413057744440194e-05,
    "out-teapot-cornell-aniso-q.pbrt-iPATH-sPOISSON-n128.exr": 0.0017637959322041124,
    "out-teapot-cornell-aniso-q.pbrt-iPATH-sRANDOM-n008.exr": 0.00044725962682846677,
    "out-teapot-cornell-aniso-q.pbrt-iPATH-sRANDOM-n032.exr": 0.00011435140132574566,
    "out-teapot-cornell-aniso-q.pbrt-iPATH-sRANDOM-n128.exr": 2.8622689632981365e-05,
    "out-teapot-cornell-aniso-q.pbrt-iPATH-sSOBOL-n008.exr": 0.00032506411509196294,
    "out-teapot-cornell-aniso-q.pbrt-iPATH-sSOBOL-n032.exr": 6.2826955432189e-05,
    "out-teapot-cornell-aniso-q.pbrt-iPATH-sSOBOL-n128.exr": 1.0116879030965157e-05,
    "out-teapot-cornell-aniso-q.pbrt-iWHITTED-sHALTON-n008.exr": 0.3045277141856278,
    "out-teapot-cornell-aniso-q.pbrt-iWHITTED-sHALTON-n032.exr": 0.07173291675886934,
    "out-teapot-cornell-aniso-q.pbrt-iWHITTED-sHALTON-n128.exr": 0.017997959610079002,
    "out-teapot-cornell-aniso-q.pbrt-iWHITTED-sPOISSON-n008.exr": 0.19528155413230672,
    "out-teapot-cornell-aniso-q.pbrt-iWHITTED-sPOISSON-n032.exr": 0.059966426311106324,
    "out-teapot-cornell-aniso-q.pbrt-iWHITTED-sPOISSON-n128.exr": 0.013045390141756074,
    "out-teapot-cornell-aniso-q.pbrt-iWHITTED-sRANDOM-n008.exr": 0.21159581006945422,
    "out-teapot-cornell-aniso-q.pbrt-iWHITTED-sRANDOM-n032.exr": 0.06618666757825958,
    "out-teapot-cornell-aniso-q.pbrt-iWHITTED-sRANDOM-n128.exr": 0.017364650023015474,
    "out-teapot-cornell-aniso-q.pbrt-iWHITTED-sSOBOL-n008.exr": 0.1713369484379018,
    "out-teapot-cornell-aniso-q.pbrt-iWHITTED-sSOBOL-n032.exr": 0.061617634231743,
    "out-teapot-cornell-aniso-q.pbrt-iWHITTED-sSOBOL-n128.exr": 0.01900167891458577
}